crxsnake/__init__.py
crxsnake/database.py
crxsnake/logger.py
crxsnake/readers.py
crxsnake/utils/__init__.py
crxsnake/utils/dayz/__init__.py
crxsnake/utils/dayz/convert.py
crxsnake/utils/dayz/hotline.py
crxsnake/utils/discord/__init__.py
crxsnake/utils/discord/cogs.py
crxsnake/utils/discord/colors.py
crxsnake/utils/discord/embed.py
crxsnake/utils/discord/parse.py
crxsnake/utils/misc.py
crxsnake/utils/steam.py
crxsnake/web/__init__.py
crxsnake/web/request.py
crxsnake-1.4.9.dist-info/LICENSE
crxsnake-1.4.9.dist-info/METADATA
crxsnake-1.4.9.dist-info/WHEEL
crxsnake-1.4.9.dist-info/RECORD
