Metadata-Version: 2.3
Name: crxsnake
Version: 1.4.9
Summary: A set of my project creation utilities
License: LICENSE
Author: CYRAX
Author-email: cherniq66@gmail.com
Requires-Python: >=3.12,<4.0
Classifier: License :: Other/Proprietary License
Classifier: Programming Language :: Python :: 3
Classifier: Programming Language :: Python :: 3.12
Classifier: Programming Language :: Python :: 3.13
Requires-Dist: aiofiles (>=24.1.0,<25.0.0)
Requires-Dist: disnake (>=2.10.1,<3.0.0)
Requires-Dist: loguru (>=0.7.3,<0.8.0)
Requires-Dist: tortoise-orm (>=0.24.0,<0.25.0)
